{
  "schemaVersion": "4.2.0",
  "routes": [
    {
      "route": "/",
      "status": "published",
      "riskLevel": "low",
      "healthStatus": "PASS",
      "nextAction": "No action"
    },
    {
      "route": "/pricing",
      "status": "published",
      "riskLevel": "low",
      "healthStatus": "PASS",
      "nextAction": "No action"
    },
    {
      "route": "/letter-of-explanation",
      "status": "published",
      "riskLevel": "medium",
      "healthStatus": "PASS",
      "nextAction": "No action"
    },
    {
      "route": "/letter-of-explanation/credit",
      "status": "published",
      "riskLevel": "regulated",
      "healthStatus": "PASS",
      "nextAction": "No action"
    },
    {
      "route": "/letter-of-explanation/eviction",
      "status": "published",
      "riskLevel": "medium",
      "healthStatus": "PASS",
      "nextAction": "No action"
    },
    {
      "route": "/letter-of-explanation/income",
      "status": "published",
      "riskLevel": "medium",
      "healthStatus": "PASS",
      "nextAction": "No action"
    },
    {
      "route": "/letter-of-explanation/employment-gap",
      "status": "published",
      "riskLevel": "medium",
      "healthStatus": "PASS",
      "nextAction": "No action"
    },
    {
      "route": "/employment-verification-letter",
      "status": "published",
      "riskLevel": "high",
      "healthStatus": "PASS",
      "nextAction": "No action"
    },
    {
      "route": "/proof-of-income-letter",
      "status": "published",
      "riskLevel": "medium",
      "healthStatus": "PASS",
      "nextAction": "No action"
    },
    {
      "route": "/credit-dispute-letter",
      "status": "published",
      "riskLevel": "regulated",
      "healthStatus": "PASS",
      "nextAction": "No action"
    },
    {
      "route": "/apartment-application",
      "status": "published",
      "riskLevel": "medium",
      "healthStatus": "PASS",
      "nextAction": "No action"
    },
    {
      "route": "/rental-application-checklist",
      "status": "published",
      "riskLevel": "medium",
      "healthStatus": "PASS",
      "nextAction": "No action"
    },
    {
      "route": "/how-to-get-approved-for-an-apartment",
      "status": "published",
      "riskLevel": "medium",
      "healthStatus": "PASS",
      "nextAction": "No action"
    },
    {
      "route": "/auto-loan-documents",
      "status": "published",
      "riskLevel": "medium",
      "healthStatus": "PASS",
      "nextAction": "No action"
    },
    {
      "route": "/car-loan-checklist",
      "status": "published",
      "riskLevel": "medium",
      "healthStatus": "PASS",
      "nextAction": "No action"
    },
    {
      "route": "/documents-needed-for-car-loan",
      "status": "published",
      "riskLevel": "medium",
      "healthStatus": "PASS",
      "nextAction": "No action"
    },
    {
      "route": "/sba-loan-checklist",
      "status": "published",
      "riskLevel": "medium",
      "healthStatus": "PASS",
      "nextAction": "No action"
    },
    {
      "route": "/business-loan-documents",
      "status": "published",
      "riskLevel": "medium",
      "healthStatus": "PASS",
      "nextAction": "No action"
    },
    {
      "route": "/mortgage-checklist",
      "status": "published",
      "riskLevel": "medium",
      "healthStatus": "PASS",
      "nextAction": "No action"
    },
    {
      "route": "/mortgage-document-checklist",
      "status": "published",
      "riskLevel": "medium",
      "healthStatus": "PASS",
      "nextAction": "No action"
    },
    {
      "route": "/important-documents-checklist",
      "status": "published",
      "riskLevel": "low",
      "healthStatus": "PASS",
      "nextAction": "No action"
    },
    {
      "route": "/moving-checklist",
      "status": "published",
      "riskLevel": "low",
      "healthStatus": "PASS",
      "nextAction": "No action"
    },
    {
      "route": "/glossary",
      "status": "published",
      "riskLevel": "low",
      "healthStatus": "PASS",
      "nextAction": "No action"
    },
    {
      "route": "/methodology",
      "status": "published",
      "riskLevel": "low",
      "healthStatus": "PASS",
      "nextAction": "No action"
    },
    {
      "route": "/checkout/success",
      "status": "published",
      "riskLevel": "medium",
      "healthStatus": "PASS",
      "nextAction": "No action"
    },
    {
      "route": "/download",
      "status": "published",
      "riskLevel": "medium",
      "healthStatus": "PASS",
      "nextAction": "No action"
    },
    {
      "route": "/privacy",
      "status": "published",
      "riskLevel": "low",
      "healthStatus": "PASS",
      "nextAction": "No action"
    },
    {
      "route": "/terms",
      "status": "published",
      "riskLevel": "low",
      "healthStatus": "PASS",
      "nextAction": "No action"
    },
    {
      "route": "/disclaimer",
      "status": "published",
      "riskLevel": "regulated",
      "healthStatus": "PASS",
      "nextAction": "No action"
    },
    {
      "route": "/refund-policy",
      "status": "published",
      "riskLevel": "low",
      "healthStatus": "PASS",
      "nextAction": "No action"
    },
    {
      "route": "/security",
      "status": "published",
      "riskLevel": "low",
      "healthStatus": "PASS",
      "nextAction": "No action"
    },
    {
      "route": "/accessibility",
      "status": "published",
      "riskLevel": "low",
      "healthStatus": "PASS",
      "nextAction": "No action"
    },
    {
      "route": "/contact",
      "status": "published",
      "riskLevel": "low",
      "healthStatus": "PASS",
      "nextAction": "No action"
    },
    {
      "route": "/editorial-policy",
      "status": "published",
      "riskLevel": "low",
      "healthStatus": "PASS",
      "nextAction": "No action"
    },
    {
      "route": "/ai-use-policy",
      "status": "published",
      "riskLevel": "medium",
      "healthStatus": "PASS",
      "nextAction": "No action"
    },
    {
      "route": "/credit-repair-disclaimer",
      "status": "published",
      "riskLevel": "regulated",
      "healthStatus": "PASS",
      "nextAction": "No action"
    },
    {
      "route": "/not-a-credit-repair-company",
      "status": "published",
      "riskLevel": "regulated",
      "healthStatus": "PASS",
      "nextAction": "No action"
    }
  ]
}
